Metadata-Version: 2.1
Name: ai-pill
Version: 0.0.0
Summary: AI-PILL
Author: CS GROUP
Author-email: loic.dumas@csgroup.eu
